CHANGELOG.md
LICENSE
MANIFEST.in
Makefile
README.md
setup.cfg
setup.py
tox.ini
wc_django_folders_backuper.egg-info/PKG-INFO
wc_django_folders_backuper.egg-info/SOURCES.txt
wc_django_folders_backuper.egg-info/dependency_links.txt
wc_django_folders_backuper.egg-info/requires.txt
wc_django_folders_backuper.egg-info/top_level.txt
wcd_folders_backuper/__init__.py
wcd_folders_backuper/admin.py
wcd_folders_backuper/apps.py
wcd_folders_backuper/conf.py
wcd_folders_backuper/discovery.py
wcd_folders_backuper/handlers.py
wcd_folders_backuper/helpers.py
wcd_folders_backuper/models.py
wcd_folders_backuper/management/__init__.py
wcd_folders_backuper/management/commands/__init__.py
wcd_folders_backuper/management/commands/folders_backup.py
wcd_folders_backuper/migrations/0001_initial.py
wcd_folders_backuper/migrations/__init__.py
wcd_folders_backuper/services/__init__.py
wcd_folders_backuper/services/backuper.py